{
	"Questions": 
	[
		{
		"QuestionID": 0,
		"Question": "First Question",
		"Choices": 
			[	
				{
				"ChoiceID": 0,
				"Choice": "Choice1"
				},
				{
				"ChoiceID": 1,
				"Choice": "Choice1"
				},
				{
				"ChoiceID": 2,
				"Choice": "Choice1"
				},
				{
				"ChoiceID": 3,
				"Choice": "Choice1"
				}
			]
		},
		{
		"QuestionID": 1,
		"Question": "Second Question",
		"Choices": 
			[	
				{
				"ChoiceID": 0,
				"Choice": "Choice1"
				},
				{
				"ChoiceID": 1,
				"Choice": "Choice1"
				},
				{
				"ChoiceID": 2,
				"Choice": "Choice1"
				},
				{
				"ChoiceID": 3,
				"Choice": "Choice1"
				}
			]
		},
		"QuestionID": 2,
		"Question": "Third Question",
		"Choices": 
			[	
				{
				"ChoiceID": 0,
				"Choice": "Choice1"
				},
				{
				"ChoiceID": 1,
				"Choice": "Choice1"
				},
				{
				"ChoiceID": 2,
				"Choice": "Choice1"
				},
				{
				"ChoiceID": 3,
				"Choice": "Choice1"
				}
			]
		},

	]
}